djwto/__init__.py
djwto/__version__.py
djwto/authentication.py
djwto/exceptions.py
djwto/models.py
djwto/settings.py
djwto/signals.py
djwto/tokens.py
djwto/urls.py
djwto/views.py
djwto/management/__init__.py
djwto/management/commands/__init__.py
djwto/management/commands/delete_tokens.py
djwto/migrations/0001_initial.py
djwto/migrations/__init__.py
djwto-0.0.4.dist-info/LICENSE
djwto-0.0.4.dist-info/METADATA
djwto-0.0.4.dist-info/WHEEL
djwto-0.0.4.dist-info/top_level.txt
djwto-0.0.4.dist-info/RECORD
